{
    "configurations": [
        {
            "name": "Mac",
            "includePath": [
                "${workspaceFolder}/**",
                "/usr/local/include/opencv4"
            ],
            "defines": [],
            "macFrameworkPath": [
                "/Applications/Xcode.app/Contents/Developer/Platforms/MacOSX.platform/Developer/SDKs/MacOSX10.14.sdk/System/Library/Frameworks"
            ],
            "compilerPath": "/usr/bin/clang",
            "cStandard": "c11",
            "cppStandard": "c++17",
            "intelliSenseMode": "clang-x64",
            "configurationProvider": "vscode-wpilib"
        },
        {
            "name": "Raspberry Pi",
            "includePath": [
                "${workspaceFolder}/**",
                "${workspaceFolder}/../pi_include/usr/include/**",
                "${workspaceFolder}/../pi_include/usr/include/arm-linux-gnueabihf/**",
                "/usr/local/include/opencv4"
            ],
            "compilerPath": "/usr/bin/gcc",
            "cStandard": "c11",
            "cppStandard": "c++17",
            "intelliSenseMode": "gcc-x64"
        },
        {
            "name": "WSL",
            "includePath": [
                "${workspaceFolder}/**",
                "/usr/include/"
            ],
            "compilerPath": "/usr/bin/gcc",
            "cStandard": "c11",
            "cppStandard": "c++17",
            "intelliSenseMode": "gcc-x64"
        }
    ],
    "version": 4
}